resonances/.env.dist
resonances/__init__.py
resonances/__main__.py
resonances/body.py
resonances/config.py
resonances/data/__init__.py
resonances/data/const.py
resonances/data/util.py
resonances/finder/__init__.py
resonances/finder/finder.py
resonances/finder/mmr_finder.py
resonances/finder/secular_finder.py
resonances/horizons.py
resonances/logger.py
resonances/matrix/matrix.py
resonances/matrix/secular_matrix.py
resonances/matrix/secular_resonances.py
resonances/matrix/three_body_matrix.py
resonances/matrix/two_body_matrix.py
resonances/resonance/__init__.py
resonances/resonance/factory.py
resonances/resonance/libration.py
resonances/resonance/mmr.py
resonances/resonance/plot.py
resonances/resonance/resonance.py
resonances/resonance/secular.py
resonances/resonance/three_body.py
resonances/resonance/two_body.py
resonances/simulation/__init__.py
resonances/simulation/body_manager.py
resonances/simulation/config.py
resonances/simulation/data_manager.py
resonances/simulation/integration.py
resonances/simulation/simulation.py
resonances-0.5.0.dist-info/LICENSE
resonances-0.5.0.dist-info/METADATA
resonances-0.5.0.dist-info/WHEEL
resonances-0.5.0.dist-info/RECORD
