Metadata-Version: 2.3
Name: resonances
Version: 0.5.0
Summary: Identification of mean-motion resonances
License: MIT
Keywords: astronomy,nbody,resonance,mmr
Author: Evgeny Smirnov
Author-email: smirik@gmail.com
Requires-Python: >=3.11,<4
Classifier: Development Status :: 4 - Beta
Classifier: Intended Audience :: Developers
Classifier: Intended Audience :: Science/Research
Classifier: License :: OSI Approved :: MIT License
Classifier: Operating System :: OS Independent
Classifier: Programming Language :: Python :: 3
Classifier: Programming Language :: Python :: 3.11
Classifier: Programming Language :: Python :: 3.12
Classifier: Programming Language :: Python :: 3.13
Classifier: Topic :: Scientific/Engineering :: Astronomy
Requires-Dist: astdys (>=0.9.4)
Requires-Dist: astropy (>=7.1.0,<8.0.0)
Requires-Dist: astroquery (>=0.4.10,<0.5.0)
Requires-Dist: lxml-html-clean (>=0.1.1,<0.5.0)
Requires-Dist: matplotlib (>=3.10.3,<4.0.0)
Requires-Dist: numpy (>=2.3.0,<3.0.0)
Requires-Dist: pandas (>=2.3.0,<3.0.0)
Requires-Dist: python-dotenv (>=1.1.0,<2.0.0)
Requires-Dist: rebound (>=4.4.8,<5.0.0)
Requires-Dist: scipy (>=1.15.3,<2.0.0)
Requires-Dist: seaborn (>=0.13.2,<0.14.0)
Requires-Dist: tqdm (>=4.67.1,<5.0.0)
Project-URL: Documentation, http://smirik.github.io/resonances/
Project-URL: Homepage, http://smirik.github.io/resonances/
Project-URL: Repository, https://github.com/smirik/resonances
